fairy/__init__.py
fairy-0.1.0.dist-info/METADATA
fairy-0.1.0.dist-info/WHEEL
fairy-0.1.0.dist-info/top_level.txt
fairy-0.1.0.dist-info/RECORD
