Metadata-Version: 2.1
Name: fairy
Version: 0.1.0
Summary: Python project.
Home-page: UNKNOWN
Author: bluelief
Author-email: UNKNOWN
License: MIT
Keywords: python
Platform: UNKNOWN
Classifier: Development Status :: 3 - Alpha
Classifier: Programming Language :: Python :: 3
Classifier: License :: OSI Approved :: MIT License
Classifier: Natural Language :: Japanese
